viseme_lipsync/model.py
viseme_lipsync/phonemedata.py
viseme_lipsync/util.py
viseme_lipsync/conformer_ppg/__init__.py
viseme_lipsync/conformer_ppg/encoder.py
viseme_lipsync/conformer_ppg/frontend.py
viseme_lipsync/conformer_ppg/model.py
viseme_lipsync/conformer_ppg/normalize.py
viseme_lipsync/conformer_ppg/layer/__init__.py
viseme_lipsync/conformer_ppg/layer/attention.py
viseme_lipsync/conformer_ppg/layer/bilstm.py
viseme_lipsync/conformer_ppg/layer/convolution.py
viseme_lipsync/conformer_ppg/layer/embedding.py
viseme_lipsync/conformer_ppg/layer/encoder_layer.py
viseme_lipsync/conformer_ppg/layer/multi_layer_conv.py
viseme_lipsync/conformer_ppg/layer/positionwise_feed_forward.py
viseme_lipsync/conformer_ppg/layer/repeat.py
viseme_lipsync/conformer_ppg/layer/subsampling.py
viseme_lipsync/conformer_ppg/layer/utils.py
viseme_lipsync/conformer_ppg/layer/vgg.py
viseme_lipsync/conformer_ppg/utils/__init__.py
viseme_lipsync/conformer_ppg/utils/klass.py
viseme_lipsync/conformer_ppg/utils/librosa.py
Viseme_Lipsync-0.0.1.dist-info/METADATA
Viseme_Lipsync-0.0.1.dist-info/WHEEL
Viseme_Lipsync-0.0.1.dist-info/top_level.txt
Viseme_Lipsync-0.0.1.dist-info/RECORD
