Metadata-Version: 2.1
Name: Viseme-Lipsync
Version: 0.0.1
Summary: Viseme-Lipsync is rule-based coarticulation model.
Keywords: viseme,phoneme,audio
Classifier: License :: OSI Approved :: BSD License
Classifier: Programming Language :: Python :: 3
Classifier: Programming Language :: Python :: 3.11
Requires-Python: >=3.11
Requires-Dist: attrs >=23.1.0
Requires-Dist: cattrs >=23.1.0
Requires-Dist: numpy >=1.23.3
Requires-Dist: pandas >=1.5.0
Requires-Dist: psutil >=5.9.8
Requires-Dist: tqdm >=4.64.1
Requires-Dist: ruamel.yaml >=0.17.21
Requires-Dist: librosa >=0.9.2
Requires-Dist: soundfile >=0.12.1
Requires-Dist: matplotlib >=3.5.2
Requires-Dist: torch >=1.12.0
Requires-Dist: torchvision >=0.13.0
Requires-Dist: torchaudio >=0.12.0
Requires-Dist: pytorch-lightning >=1.8.1
Requires-Dist: tensorboard >=2.9.1
Provides-Extra: dev
Requires-Dist: nface-atl[inference] ; extra == 'dev'
Requires-Dist: isort ; extra == 'dev'
Requires-Dist: black ; extra == 'dev'
Requires-Dist: flake8 ; extra == 'dev'
Requires-Dist: pylint ; extra == 'dev'
Requires-Dist: pyright ; extra == 'dev'
Requires-Dist: pre-commit ; extra == 'dev'
Provides-Extra: test
Requires-Dist: tox ; extra == 'test'
Requires-Dist: pytest >=7.0.0 ; extra == 'test'
Requires-Dist: pytest-cov ; extra == 'test'
Requires-Dist: pytest-asyncio ; extra == 'test'
Requires-Dist: pytest-benchmark ; extra == 'test'
